[{"__symbolic":"module","version":3,"metadata":{"Report":{"__symbolic":"class","members":{"__ctor__":[{"__symbolic":"constructor","parameters":[{"__symbolic":"reference","name":"string"}]}]}},"CarPark":{"__symbolic":"class","members":{"__ctor__":[{"__symbolic":"constructor"}]}},"Scheduling":{"__symbolic":"class","decorators":[{"__symbolic":"call","expression":{"__symbolic":"reference","module":"@angular/core","name":"Injectable"}},{"__symbolic":"call","expression":{"__symbolic":"reference","module":"../index","name":"EndPoint"},"arguments":[{"Create":"http://requestb.in/10h1r4i1","Read":"","Update":"","Delete":""}]}],"members":{"__ctor__":[{"__symbolic":"constructor"}],"id":[{"__symbolic":"property","decorators":[{"__symbolic":"call","expression":{"__symbolic":"reference","module":"../index","name":"Id"}}]}],"name":[{"__symbolic":"property","decorators":[{"__symbolic":"call","expression":{"__symbolic":"reference","module":"../index","name":"InputType"},"arguments":[{"name":"User:","type":"text","defaultValue":"Cláudio Margulhano","readOnly":true,"autoWidth":true,"order":0}]}]}],"password":[{"__symbolic":"property","decorators":[{"__symbolic":"call","expression":{"__symbolic":"reference","module":"../index","name":"InputType"},"arguments":[{"name":"Password:","type":"password","defaultValue":"123","autoWidth":true,"order":1}]}]}],"admin":[{"__symbolic":"property","decorators":[{"__symbolic":"call","expression":{"__symbolic":"reference","module":"../index","name":"InputType"},"arguments":[{"name":"Admin:","type":"checkbox","defaultValue":true,"order":2}]}]}],"reports":[{"__symbolic":"property","decorators":[{"__symbolic":"call","expression":{"__symbolic":"reference","module":"../index","name":"MultiSelect"},"arguments":[{"url":"http://www.mocky.io/v2/58822b002800002d05cbd40d","modelSelect":"reportList","modelSelectClazz":{"__symbolic":"reference","name":"Report"},"modelSelectValue":"id","modelSelectLabel":"name","disabled":true,"order":3}]}]}],"mails":[{"__symbolic":"property","decorators":[{"__symbolic":"call","expression":{"__symbolic":"reference","module":"../index","name":"Chips"},"arguments":[{"disabled":false,"autoWidth":true,"order":4}]}]}],"carParks":[{"__symbolic":"property","decorators":[{"__symbolic":"call","expression":{"__symbolic":"reference","module":"../index","name":"MultiSelect"},"arguments":[{"url":"http://www.mocky.io/v2/583ecaf7240000f20383b35d","modelSelectClazz":{"__symbolic":"reference","name":"CarPark"},"modelSelectValue":"id","modelSelectLabel":"name","order":6}]}]}],"period":[{"__symbolic":"property","decorators":[{"__symbolic":"call","expression":{"__symbolic":"reference","module":"../index","name":"Select"},"arguments":[{"values":[{"value":"1","label":"Value 1","$quoted$":["value","label"]},{"value":"2","label":"Value 2","$quoted$":["value","label"]},{"value":"3","label":"Value 3","$quoted$":["value","label"]}],"defaultValue":2,"order":5}]}]}],"date1":[{"__symbolic":"property","decorators":[{"__symbolic":"call","expression":{"__symbolic":"reference","module":"../index","name":"Calendar"},"arguments":[{"disabled":false,"autoWidth":true,"order":7,"format":"DD/MM/YYYY"}]}]}],"date2":[{"__symbolic":"property","decorators":[{"__symbolic":"call","expression":{"__symbolic":"reference","module":"../index","name":"Calendar"},"arguments":[{"disabled":false,"autoWidth":true,"order":7,"format":"DD/MM/YYYY"}]}]}]}}}},{"__symbolic":"module","version":1,"metadata":{"Report":{"__symbolic":"class","members":{"__ctor__":[{"__symbolic":"constructor","parameters":[{"__symbolic":"reference","name":"string"}]}]}},"CarPark":{"__symbolic":"class","members":{"__ctor__":[{"__symbolic":"constructor"}]}},"Scheduling":{"__symbolic":"class","decorators":[{"__symbolic":"call","expression":{"__symbolic":"reference","module":"@angular/core","name":"Injectable"}},{"__symbolic":"call","expression":{"__symbolic":"reference","module":"../index","name":"EndPoint"},"arguments":[{"Create":"http://requestb.in/10h1r4i1","Read":"","Update":"","Delete":""}]}],"members":{"__ctor__":[{"__symbolic":"constructor"}],"id":[{"__symbolic":"property","decorators":[{"__symbolic":"call","expression":{"__symbolic":"reference","module":"../index","name":"Id"}}]}],"name":[{"__symbolic":"property","decorators":[{"__symbolic":"call","expression":{"__symbolic":"reference","module":"../index","name":"InputType"},"arguments":[{"name":"User:","type":"text","defaultValue":"Cláudio Margulhano","readOnly":true,"autoWidth":true,"order":0}]}]}],"password":[{"__symbolic":"property","decorators":[{"__symbolic":"call","expression":{"__symbolic":"reference","module":"../index","name":"InputType"},"arguments":[{"name":"Password:","type":"password","defaultValue":"123","autoWidth":true,"order":1}]}]}],"admin":[{"__symbolic":"property","decorators":[{"__symbolic":"call","expression":{"__symbolic":"reference","module":"../index","name":"InputType"},"arguments":[{"name":"Admin:","type":"checkbox","defaultValue":true,"order":2}]}]}],"reports":[{"__symbolic":"property","decorators":[{"__symbolic":"call","expression":{"__symbolic":"reference","module":"../index","name":"MultiSelect"},"arguments":[{"url":"http://www.mocky.io/v2/58822b002800002d05cbd40d","modelSelect":"reportList","modelSelectClazz":{"__symbolic":"reference","name":"Report"},"modelSelectValue":"id","modelSelectLabel":"name","disabled":true,"order":3}]}]}],"mails":[{"__symbolic":"property","decorators":[{"__symbolic":"call","expression":{"__symbolic":"reference","module":"../index","name":"Chips"},"arguments":[{"disabled":false,"autoWidth":true,"order":4}]}]}],"carParks":[{"__symbolic":"property","decorators":[{"__symbolic":"call","expression":{"__symbolic":"reference","module":"../index","name":"MultiSelect"},"arguments":[{"url":"http://www.mocky.io/v2/583ecaf7240000f20383b35d","modelSelectClazz":{"__symbolic":"reference","name":"CarPark"},"modelSelectValue":"id","modelSelectLabel":"name","order":6}]}]}],"period":[{"__symbolic":"property","decorators":[{"__symbolic":"call","expression":{"__symbolic":"reference","module":"../index","name":"Select"},"arguments":[{"values":[{"value":"1","label":"Value 1"},{"value":"2","label":"Value 2"},{"value":"3","label":"Value 3"}],"defaultValue":2,"order":5}]}]}],"date1":[{"__symbolic":"property","decorators":[{"__symbolic":"call","expression":{"__symbolic":"reference","module":"../index","name":"Calendar"},"arguments":[{"disabled":false,"autoWidth":true,"order":7,"format":"DD/MM/YYYY"}]}]}],"date2":[{"__symbolic":"property","decorators":[{"__symbolic":"call","expression":{"__symbolic":"reference","module":"../index","name":"Calendar"},"arguments":[{"disabled":false,"autoWidth":true,"order":7,"format":"DD/MM/YYYY"}]}]}]}}}}]